suricata_threatbus/__init__.py
suricata_threatbus/suricata.py
suricata_threatbus-2022.5.16.dist-info/METADATA
suricata_threatbus-2022.5.16.dist-info/WHEEL
suricata_threatbus-2022.5.16.dist-info/entry_points.txt
suricata_threatbus-2022.5.16.dist-info/top_level.txt
suricata_threatbus-2022.5.16.dist-info/RECORD
